pytgrd/__init__.py
pytgrd/by.py
pytgrd/core.py
pytgrd/utils.py
pytgrd-1.0.0.dist-info/METADATA
pytgrd-1.0.0.dist-info/WHEEL
pytgrd-1.0.0.dist-info/top_level.txt
pytgrd-1.0.0.dist-info/RECORD
