Metadata-Version: 2.1
Name: pytgrd
Version: 1.0.0
Summary: UNKNOWN
Author: Huang Bo-Xuan
Author-email: r09142003@gmail.com
License: UNKNOWN
Platform: UNKNOWN
Requires-Dist: seaborn
Requires-Dist: matplotlib
Requires-Dist: pandas
